humanlayer-0.7.9.dist-info/METADATA
humanlayer-0.7.9.dist-info/WHEEL
humanlayer-0.7.9.dist-info/entry_points.txt
humanlayer-0.7.9.dist-info/licenses/LICENSE
humanlayer/__init__.py
humanlayer/__main__.py
humanlayer/cli/__init__.py
humanlayer/cli/main.py
humanlayer/core/__init__.py
humanlayer/core/approval.py
humanlayer/core/approval_human_as_tool_test.py
humanlayer/core/approval_require_approval_test.py
humanlayer/core/approval_resolve_backend_test.py
humanlayer/core/async_approval.py
humanlayer/core/async_approval_human_as_tool_test.py
humanlayer/core/async_approval_require_approval_test.py
humanlayer/core/async_cloud.py
humanlayer/core/async_protocol.py
humanlayer/core/async_resolve_backend_test.py
humanlayer/core/cloud.py
humanlayer/core/models.py
humanlayer/core/models_agent_webhook.py
humanlayer/core/models_test.py
humanlayer/core/protocol.py
humanlayer/py.typed
humanlayer/testing/__init__.py
humanlayer-0.7.9.dist-info/RECORD
