Metadata-Version: 2.1
Name: humanlayer
Version: 0.7.9
Summary: humanlayer
Author-Email: humanlayer authors <dexter@metalytics.dev>
Project-URL: repository, https://github.com/humanlayer/humanlayer
Requires-Python: <4.0,>=3.10
Requires-Dist: pydantic<3.0.0,>=2.8.2
Requires-Dist: requests<3.0.0,>=2.32.3
Requires-Dist: python-slugify<9.0.0,>=8.0.4
Requires-Dist: python-dotenv<2.0.0,>=1.0.1
Requires-Dist: click<9.0.0,>=8.1.7
Requires-Dist: aiohttp<4.0.0,>=3.11.10
